test_hive_2_ti_client/__init__.py
test_hive_2_ti_client/api_client.py
test_hive_2_ti_client/api_response.py
test_hive_2_ti_client/configuration.py
test_hive_2_ti_client/exceptions.py
test_hive_2_ti_client/py.typed
test_hive_2_ti_client/rest.py
test_hive_2_ti_client/api/__init__.py
test_hive_2_ti_client/api/gifs_api.py
test_hive_2_ti_client/api/stickers_api.py
test_hive_2_ti_client/models/__init__.py
test_hive_2_ti_client/models/get_gifs_by_id200_response.py
test_hive_2_ti_client/models/gif.py
test_hive_2_ti_client/models/gif_images.py
test_hive_2_ti_client/models/gif_images_downsized.py
test_hive_2_ti_client/models/gif_images_downsized_large.py
test_hive_2_ti_client/models/gif_images_downsized_medium.py
test_hive_2_ti_client/models/gif_images_downsized_small.py
test_hive_2_ti_client/models/gif_images_downsized_still.py
test_hive_2_ti_client/models/gif_images_fixed_height.py
test_hive_2_ti_client/models/gif_images_fixed_height_downsampled.py
test_hive_2_ti_client/models/gif_images_fixed_height_small.py
test_hive_2_ti_client/models/gif_images_fixed_height_small_still.py
test_hive_2_ti_client/models/gif_images_fixed_height_still.py
test_hive_2_ti_client/models/gif_images_fixed_width.py
test_hive_2_ti_client/models/gif_images_fixed_width_downsampled.py
test_hive_2_ti_client/models/gif_images_fixed_width_small.py
test_hive_2_ti_client/models/gif_images_fixed_width_small_still.py
test_hive_2_ti_client/models/gif_images_fixed_width_still.py
test_hive_2_ti_client/models/gif_images_looping.py
test_hive_2_ti_client/models/gif_images_original.py
test_hive_2_ti_client/models/gif_images_original_still.py
test_hive_2_ti_client/models/gif_images_preview.py
test_hive_2_ti_client/models/gif_images_preview_gif.py
test_hive_2_ti_client/models/image.py
test_hive_2_ti_client/models/meta.py
test_hive_2_ti_client/models/pagination.py
test_hive_2_ti_client/models/random_gif200_response.py
test_hive_2_ti_client/models/user.py
test_hive_2_ti_client-1.0.0.dist-info/METADATA
test_hive_2_ti_client-1.0.0.dist-info/WHEEL
test_hive_2_ti_client-1.0.0.dist-info/top_level.txt
test_hive_2_ti_client-1.0.0.dist-info/RECORD
